django_crontab/__init__.py
django_crontab/app_settings.py
django_crontab/crontab.py
django_crontab/models.py
django_crontab/management/__init__.py
django_crontab/management/commands/__init__.py
django_crontab/management/commands/crontab.py
django_crontab-0.7.0.dist-info/DESCRIPTION.rst
django_crontab-0.7.0.dist-info/METADATA
django_crontab-0.7.0.dist-info/RECORD
django_crontab-0.7.0.dist-info/WHEEL
django_crontab-0.7.0.dist-info/metadata.json
django_crontab-0.7.0.dist-info/top_level.txt
